elevan_labs_mcp/__init__.py
elevan_labs_mcp/config.py
elevan_labs_mcp/server.py
elevan_labs_mcp-0.1.1.dist-info/METADATA
elevan_labs_mcp-0.1.1.dist-info/WHEEL
elevan_labs_mcp-0.1.1.dist-info/entry_points.txt
elevan_labs_mcp-0.1.1.dist-info/RECORD
