Metadata-Version: 2.4
Name: elevan-labs-mcp
Version: 0.1.1
Summary: MCP server for ElevenLabs text-to-speech API integration
Project-URL: Homepage, https://github.com/mafzaal/elevan-labs-mcp
Project-URL: Documentation, https://github.com/mafzaal/elevan-labs-mcp#readme
Project-URL: Repository, https://github.com/mafzaal/elevan-labs-mcp.git
Project-URL: Bug Tracker, https://github.com/mafzaal/elevan-labs-mcp/issues
Project-URL: Changelog, https://github.com/mafzaal/elevan-labs-mcp/blob/main/CHANGELOG.md
Author-email: Muhammad Afzaal <mo@thedataguy.pro>
Maintainer-email: Muhammad Afzaal <mo@thedataguy.pro>
License: MIT
Keywords: ai,elevenlabs,mcp,text-to-speech,tts,voice
Classifier: Development Status :: 3 - Alpha
Classifier: Intended Audience :: Developers
Classifier: License :: OSI Approved :: MIT License
Classifier: Operating System :: OS Independent
Classifier: Programming Language :: Python :: 3
Classifier: Programming Language :: Python :: 3.13
Classifier: Topic :: Internet :: WWW/HTTP :: Dynamic Content
Classifier: Topic :: Multimedia :: Sound/Audio :: Speech
Classifier: Topic :: Software Development :: Libraries :: Python Modules
Requires-Python: >=3.13
Requires-Dist: elevenlabs>=2.5.0
Requires-Dist: httpx>=0.25.0
Requires-Dist: mcp>=1.0.0
Requires-Dist: pydantic>=2.0.0
Requires-Dist: python-dotenv>=1.1.1
Provides-Extra: dev
Requires-Dist: black>=23.0.0; extra == 'dev'
Requires-Dist: flake8>=6.0.0; extra == 'dev'
Requires-Dist: isort>=5.12.0; extra == 'dev'
Requires-Dist: mypy>=1.0.0; extra == 'dev'
Requires-Dist: pre-commit>=3.0.0; extra == 'dev'
Requires-Dist: pytest-asyncio>=0.21.0; extra == 'dev'
Requires-Dist: pytest>=7.0.0; extra == 'dev'
